dibs_computing_core/.sourcery.yaml
dibs_computing_core/Vagrantfile
dibs_computing_core/__init__.py
dibs_computing_core/bootstrap.sh
dibs_computing_core/iso_simulator/__init__.py
dibs_computing_core/iso_simulator/emission_system.py
dibs_computing_core/iso_simulator/supply_system.py
dibs_computing_core/iso_simulator/building_simulator/__init__.py
dibs_computing_core/iso_simulator/building_simulator/simulator.py
dibs_computing_core/iso_simulator/data_source/__init__.py
dibs_computing_core/iso_simulator/data_source/datasource.py
dibs_computing_core/iso_simulator/dibs/__.init__.py
dibs_computing_core/iso_simulator/dibs/dibs.py
dibs_computing_core/iso_simulator/dibs/dibs_utils/__init__.py
dibs_computing_core/iso_simulator/dibs/dibs_utils/dibs_auxiliary_functions.py
dibs_computing_core/iso_simulator/exceptions/building_not_heated_exception.py
dibs_computing_core/iso_simulator/exceptions/ghg_emission.py
dibs_computing_core/iso_simulator/exceptions/plz_exception.py
dibs_computing_core/iso_simulator/exceptions/uk_or_hk_exception.py
dibs_computing_core/iso_simulator/exceptions/usage_time_exception.py
dibs_computing_core/iso_simulator/model/ResultOutput.py
dibs_computing_core/iso_simulator/model/__init__.py
dibs_computing_core/iso_simulator/model/building.py
dibs_computing_core/iso_simulator/model/calculations_sum.py
dibs_computing_core/iso_simulator/model/epw_file.py
dibs_computing_core/iso_simulator/model/hours_result.py
dibs_computing_core/iso_simulator/model/location.py
dibs_computing_core/iso_simulator/model/primary_energy_and_emission_factors.py
dibs_computing_core/iso_simulator/model/schedule_name.py
dibs_computing_core/iso_simulator/model/summary_result.py
dibs_computing_core/iso_simulator/model/weather_data.py
dibs_computing_core/iso_simulator/model/window.py
dibs_computing_core-1.0.0.dist-info/LICENSE
dibs_computing_core-1.0.0.dist-info/WHEEL
dibs_computing_core-1.0.0.dist-info/METADATA
dibs_computing_core-1.0.0.dist-info/RECORD
